[
    {
        "collectionGroup": "matches",
        "queryScope": "COLLECTION",
        "fields": [
            {
                "fieldPath": "status",
                "order": "ASCENDING"
            },
            {
                "fieldPath": "kickoffTime",
                "order": "ASCENDING"
            }
        ]
    },
    {
        "collectionGroup": "matches",
        "queryScope": "COLLECTION",
        "fields": [
            {
                "fieldPath": "status",
                "order": "ASCENDING"
            },
            {
                "fieldPath": "spotsLeft",
                "order": "DESCENDING"
            }
        ]
    },
    {
        "collectionGroup": "matches",
        "queryScope": "COLLECTION",
        "fields": [
            {
                "fieldPath": "status",
                "order": "ASCENDING"
            },
            {
                "fieldPath": "format",
                "order": "ASCENDING"
            },
            {
                "fieldPath": "kickoffTime",
                "order": "ASCENDING"
            }
        ]
    },
    {
        "collectionGroup": "matches",
        "queryScope": "COLLECTION",
        "fields": [
            {
                "fieldPath": "status",
                "order": "ASCENDING"
            },
            {
                "fieldPath": "skillLevel",
                "order": "ASCENDING"
            },
            {
                "fieldPath": "kickoffTime",
                "order": "ASCENDING"
            }
        ]
    },
    {
        "collectionGroup": "matches",
        "queryScope": "COLLECTION",
        "fields": [
            {
                "fieldPath": "status",
                "order": "ASCENDING"
            },
            {
                "fieldPath": "format",
                "order": "ASCENDING"
            },
            {
                "fieldPath": "skillLevel",
                "order": "ASCENDING"
            },
            {
                "fieldPath": "kickoffTime",
                "order": "ASCENDING"
            }
        ]
    },
    {
        "collectionGroup": "matches",
        "queryScope": "COLLECTION",
        "fields": [
            {
                "fieldPath": "status",
                "order": "ASCENDING"
            },
            {
                "fieldPath": "kickoffTime",
                "order": "ASCENDING"
            },
            {
                "fieldPath": "kickoffTime",
                "order": "ASCENDING"
            }
        ]
    },
    {
        "collectionGroup": "notifications",
        "queryScope": "COLLECTION",
        "fields": [
            {
                "fieldPath": "userId",
                "order": "ASCENDING"
            },
            {
                "fieldPath": "createdAt",
                "order": "DESCENDING"
            }
        ]
    },
    {
        "collectionGroup": "posts",
        "queryScope": "COLLECTION",
        "fields": [
            {
                "fieldPath": "createdAt",
                "order": "DESCENDING"
            }
        ]
    }
]